crosswordpy/__init__.py
crosswordpy/game.py
crosswordpy/py.typed
crosswordpy/crosswordpy_data/000.txt
crosswordpy/crosswordpy_data/001.txt
crosswordpy/crosswordpy_data/002.txt
crosswordpy/crosswordpy_data/003.txt
crosswordpy/crosswordpy_data/004.txt
crosswordpy/crosswordpy_data/005.txt
crosswordpy/crosswordpy_data/006.txt
crosswordpy-0.2.1.dist-info/METADATA
crosswordpy-0.2.1.dist-info/WHEEL
crosswordpy-0.2.1.dist-info/entry_points.txt
crosswordpy-0.2.1.dist-info/licenses/LICENSE
crosswordpy-0.2.1.dist-info/RECORD
