Metadata-Version: 2.4
Name: crosswordpy
Version: 0.2.1
Summary: No Hint Crossword Puzzle
Project-URL: homepage, https://github.com/SaitoTsutomu/crosswordpy
Author-email: Saito Tsutomu <tsutomu7@hotmail.co.jp>
License-File: LICENSE
Classifier: Development Status :: 1 - Planning
Classifier: License :: OSI Approved :: Apache Software License
Classifier: Programming Language :: Python
Classifier: Topic :: Scientific/Engineering
Classifier: Topic :: Software Development
Requires-Python: >=3.11
Requires-Dist: pygame>=2.6.1
